pcdl/VERSION.py
pcdl/__init__.py
pcdl/commandline.py
pcdl/imagine.py
pcdl/neuromancer.py
pcdl/output_data.py
pcdl/pdplt.py
pcdl/timeseries.py
pcdl/timestep.py
pcdl-4.1.0.dist-info/METADATA
pcdl-4.1.0.dist-info/WHEEL
pcdl-4.1.0.dist-info/entry_points.txt
pcdl-4.1.0.dist-info/licenses/LICENSE
pcdl-4.1.0.dist-info/RECORD
