Metadata-Version: 2.4
Name: pcdl
Version: 4.1.0
Summary: physicell data loader (pcdl) provides a platform independent, python3 based, pip installable interface to load output, generated with the PhysiCell agent based modeling framework, into python3.
Project-URL: Homepage lab, http://www.mathcancer.org/
Project-URL: Homepage project, http://physicell.org/
Project-URL: Hompage, https://github.com/elmbeech/physicelldataloader
Project-URL: Documentation, https://github.com/elmbeech/physicelldataloader/tree/master/man
Project-URL: Issues, https://github.com/elmbeech/physicelldataloader/issues
Project-URL: Source, https://github.com/elmbeech/physicelldataloader
Author-email: Elmar Bucher <epbucher@iu.edu>
Maintainer-email: Elmar Bucher <epbucher@iu.edu>
License-Expression: BSD-3-Clause
License-File: LICENSE
Keywords: analysis,data,physicell,python3
Classifier: Development Status :: 3 - Alpha
Classifier: Intended Audience :: Developers
Classifier: Intended Audience :: Science/Research
Classifier: License :: OSI Approved :: BSD License
Classifier: Programming Language :: Python :: 3 :: Only
Classifier: Topic :: Scientific/Engineering :: Bio-Informatics
Requires-Python: <4,>=3.11
Requires-Dist: anndata>=0.10.8
Requires-Dist: bioio-ome-tiff
Requires-Dist: bioio>=1.2.1
Requires-Dist: geopandas>=0.14
Requires-Dist: matplotlib
Requires-Dist: neuroglancer
Requires-Dist: numpy
Requires-Dist: pandas>=2.2.2
Requires-Dist: requests
Requires-Dist: scikit-image>=0.24.0
Requires-Dist: scipy>=1.13.0
Requires-Dist: shapely>=2.0.1
Requires-Dist: spatialdata>=0.6.0
Requires-Dist: vtk
